{"authors": [{"first": "Mohammadbagher", "last": "Fotouhi"}, {"first": "Ruixin", "last": "Niu"}, {"first": "Wei", "last": "Cheng"}], "title": "An Accurate Smartphone Ranging System", "year": "2018", "isbn": "9781450357203", "publisher": "Association for Computing Machinery", "address": "New York, NY, USA", "url": "https://doi.org/10.1145/3210240.3210815", "doi": "10.1145/3210240.3210815", "abstract": "In this poster, an accurate distance ranging system for off-the-shelf smartphones is introduced. Two ranging methods, namely improved Microsoft Beep-Beep and our Single-Beep, are developed and evaluated on 6 different Android phones.", "booktitle": "Proceedings of the 16th Annual International Conference on Mobile Systems, Applications, and Services", "numpages": "1", "location": "Munich, Germany", "series": "MobiSys '18"}