{"authors": [{"first": "Larry Richard", "last": "Carley"}], "title": "Chip-to-Chip RF Communications and Power Delivery via On-Chip Antennas", "year": "2018", "isbn": "9781450359030", "publisher": "Association for Computing Machinery", "address": "New York, NY, USA", "url": "https://doi.org/10.1145/3241539.3270100", "doi": "10.1145/3241539.3270100", "booktitle": "Proceedings of the 24th Annual International Conference on Mobile Computing and Networking", "numpages": "2", "keywords": ["on-chip antennas", "chip-to-chip RF communication", "wireless power delivery", "mems post-processing", "RFIDs", "system-on-chip (SOC)"], "location": "New Delhi, India", "series": "MobiCom '18"}