{"authors": [{"first": "Hyungkun", "last": "Jung"}, {"first": "Kang-Woo", "last": "Lee"}, {"first": "Eun-Sun", "last": "Cho"}], "title": "Outlier Detection for Ship Trajectory Prediction (Poster)", "year": "2019", "isbn": "9781450366618", "publisher": "Association for Computing Machinery", "address": "New York, NY, USA", "url": "https://doi.org/10.1145/3307334.3328639", "doi": "10.1145/3307334.3328639", "booktitle": "Proceedings of the 17th Annual International Conference on Mobile Systems, Applications, and Services", "numpages": "2", "keywords": ["ship trajectory", "outlier detection", "trajectory clustering"], "location": "Seoul, Republic of Korea", "series": "MobiSys '19"}