{"authors": [{"first": "Gy\\\"{o}rgy", "last": "Kalm\\'{a}r"}, {"first": "George", "last": "Wittemyer"}, {"first": "P\\'{e}ter", "last": "V\\\"{o}lgyesi"}, {"first": "Henrik Barner", "last": "Rasmussen"}, {"first": "Mikl\\'{o}s", "last": "Mar\\'{o}ti"}, {"first": "\\'{A}kos", "last": "L\\'{e}deczi"}], "title": "Animal-Borne Acoustic Gunshot Detector (Poster)", "year": "2019", "isbn": "9781450366618", "publisher": "Association for Computing Machinery", "address": "New York, NY, USA", "url": "https://doi.org/10.1145/3307334.3328634", "doi": "10.1145/3307334.3328634", "booktitle": "Proceedings of the 17th Annual International Conference on Mobile Systems, Applications, and Services", "numpages": "2", "keywords": ["poaching", "shockwave", "low-power", "acoustics", "wearable"], "location": "Seoul, Republic of Korea", "series": "MobiSys '19"}