{"authors": [{"first": "Yotam", "last": "Harchol"}, {"first": "Dirk", "last": "Bergemann"}, {"first": "Nick", "last": "Feamster"}, {"first": "Eric", "last": "Friedman"}, {"first": "Arvind", "last": "Krishnamurthy"}, {"first": "Aurojit", "last": "a"}, {"first": "Sylvia", "last": "Ratnasamy"}, {"first": "Michael", "last": "Schapira"}, {"first": "Scott", "last": "Shenker"}], "title": "A Public Option for the Core", "year": "2020", "isbn": "9781450379557", "publisher": "Association for Computing Machinery", "address": "New York, NY, USA", "url": "https://doi.org/10.1145/3387514.3405875", "doi": "10.1145/3387514.3405875", "booktitle": "Proceedings of the Annual Conference of the ACM Special Interest Group on Data Communication on the Applications, Technologies, Architectures, and Protocols for Computer Communication", "numpages": "13", "keywords": ["Internet transit", "Internet infrastructure", "Network neutrality"], "location": "Virtual Event, USA", "series": "SIGCOMM '20"}