{"authors": [{"first": "Long", "last": "Huang"}, {"first": "Zhen", "last": "Meng"}, {"first": "Zeyu", "last": "Deng"}, {"first": "Chen", "last": "Wang"}, {"first": "Liying", "last": "Li"}, {"first": "Guodong", "last": "Zhao"}], "title": "Extracting Human Behavioral Biometrics from Robot Motions", "year": "2021", "isbn": "9781450383424", "publisher": "Association for Computing Machinery", "address": "New York, NY, USA", "url": "https://doi.org/10.1145/3447993.3482860", "booktitle": "Proceedings of the 27th Annual International Conference on Mobile Computing and Networking", "numpages": "3"}